xor_delta/__init__.py
xor_delta/__main__.py
xor_delta/bench_files.py
xor_delta/cli.py
xor_delta/workload.py
xor_delta/xor_delta.py
xor_delta-1.0.0.dist-info/METADATA
xor_delta-1.0.0.dist-info/WHEEL
xor_delta-1.0.0.dist-info/entry_points.txt
xor_delta-1.0.0.dist-info/RECORD
