Metadata-Version: 2.4
Name: xor-delta
Version: 1.0.0
Summary: Reversible adjacent XOR differencing transform algo
License: MIT
Author: DJ Stomp
Author-email: 85457381+DJStompZone@users.noreply.github.com
Requires-Python: >=3.10,<4.0
Classifier: License :: OSI Approved :: MIT License
Classifier: Programming Language :: Python :: 3
Classifier: Programming Language :: Python :: 3.10
Classifier: Programming Language :: Python :: 3.11
Classifier: Programming Language :: Python :: 3.12
Classifier: Programming Language :: Python :: 3.13
Classifier: Programming Language :: Python :: 3.14
Requires-Dist: tqdm (>=4.67.1,<5.0.0)
